{
  "unversionedId": "tutorial/deploy-your-squid",
  "id": "tutorial/deploy-your-squid",
  "title": "Deploy your first Squid",
  "description": "Launch a Squid node hosted in the Cloud by Subsquid",
  "source": "@site/docs/tutorial/deploy-your-squid.md",
  "sourceDirName": "tutorial",
  "slug": "/tutorial/deploy-your-squid",
  "permalink": "/docs/tutorial/deploy-your-squid",
  "draft": false,
  "tags": [],
  "version": "current",
  "frontMatter": {
    "description": "Launch a Squid node hosted in the Cloud by Subsquid"
  },
  "sidebar": "tutorialSidebar",
  "previous": {
    "title": "Create an EVM-processing Squid",
    "permalink": "/docs/tutorial/create-an-evm-processing-squid"
  },
  "next": {
    "title": "Development Environment set up",
    "permalink": "/docs/tutorial/development-environment-set-up"
  }
}