{
  "unversionedId": "overview",
  "id": "overview",
  "title": "Overview",
  "description": "This documentation provides information for all degrees of expertise, varying from complete beginner, to those who only need a refresher on specific commands.",
  "source": "@site/docs/index.md",
  "sourceDirName": ".",
  "slug": "/",
  "permalink": "/docs/",
  "draft": false,
  "tags": [],
  "version": "current",
  "frontMatter": {
    "id": "overview",
    "title": "Overview"
  },
  "sidebar": "tutorialSidebar",
  "previous": {
    "title": "Where do I get a type bundle for my chain?",
    "permalink": "/docs/faq/where-do-i-get-a-type-bundle-for-my-chain"
  },
  "next": {
    "title": "Key Concepts",
    "permalink": "/docs/key-concepts/"
  }
}